oidc_token_proxy/__init__.py
oidc_token_proxy/api.py
oidc_token_proxy/issuer.py
oidc_token_proxy/jwks_cache.py
oidc_token_proxy-0.1.0.dist-info/METADATA
oidc_token_proxy-0.1.0.dist-info/WHEEL
oidc_token_proxy-0.1.0.dist-info/entry_points.txt
oidc_token_proxy-0.1.0.dist-info/licenses/LICENSE.txt
oidc_token_proxy-0.1.0.dist-info/RECORD
