Metadata-Version: 2.4
Name: oidc-token-proxy
Version: 0.1.0
Summary: An OIDC issuer that can re-mints tokens from a verified upstream issuer.
Project-URL: Repository, https://github.com/mmerickel/oidc-token-proxy
Project-URL: Issues, https://github.com/mmerickel/oidc-token-proxy/issues
Author-email: Michael Merickel <oss@m.merickel.org>
License-Expression: MIT
License-File: LICENSE.txt
Keywords: id token,issuer,oauth,oidc,proxy
Classifier: Development Status :: 4 - Beta
Classifier: Intended Audience :: Developers
Classifier: Programming Language :: Python :: 3
Classifier: Programming Language :: Python :: 3.13
Classifier: Topic :: Software Development :: Build Tools
Requires-Python: >=3.13
Requires-Dist: attrs>=25.1.0
Requires-Dist: hupper>=1.12.1
Requires-Dist: jwcrypto>=1.5.6
Requires-Dist: pyramid>=2.0.2
Requires-Dist: subparse>=0.6
Provides-Extra: app
Requires-Dist: plaster-pastedeploy>=1.0.1; extra == 'app'
Requires-Dist: request-id>=1.0.1; extra == 'app'
Requires-Dist: waitress>=3.0.2; extra == 'app'
